CHANGELOG.txt
LICENSE.txt
MANIFEST.in
README.txt
setup.py
test.py
pw_gen/__init__.py
pw_gen.egg-info/PKG-INFO
pw_gen.egg-info/SOURCES.txt
pw_gen.egg-info/dependency_links.txt
pw_gen.egg-info/top_level.txt