Metadata-Version: 1.1
Name: pw-gen
Version: 0.1.1
Summary: A library for generating secure passwords
Home-page: https://github.com/lunAr-creator/password_generator
Author: Soma Benfell
Author-email: lunArcreator3@gmail.com
License: MIT
Keywords: password
Platform: UNKNOWN
Classifier: Development Status :: 5 - Production/Stable
Classifier: Intended Audience :: Education
Classifier: Operating System :: Microsoft :: Windows :: Windows 10
Classifier: License :: OSI Approved :: MIT License
Classifier: Programming Language :: Python :: 3
